MKVBatchMultiplex/__init__.py
MKVBatchMultiplex/config.py
MKVBatchMultiplex/icons.qrc
MKVBatchMultiplex/main.py
MKVBatchMultiplex/dataset/TableData.py
MKVBatchMultiplex/dataset/__init__.py
MKVBatchMultiplex/dataset/tableHeaders.py
MKVBatchMultiplex/delegates/__init__.py
MKVBatchMultiplex/delegates/delegates.py
MKVBatchMultiplex/html/.buildinfo
MKVBatchMultiplex/html/.nojekyll
MKVBatchMultiplex/html/CHANGELOG.html
MKVBatchMultiplex/html/LICENSE.html
MKVBatchMultiplex/html/README.html
MKVBatchMultiplex/html/acknowledgements.html
MKVBatchMultiplex/html/genindex.html
MKVBatchMultiplex/html/gettingstarted.html
MKVBatchMultiplex/html/index.html
MKVBatchMultiplex/html/installation.html
MKVBatchMultiplex/html/introduction.html
MKVBatchMultiplex/html/objects.inv
MKVBatchMultiplex/html/search.html
MKVBatchMultiplex/html/searchindex.js
MKVBatchMultiplex/html/using.html
MKVBatchMultiplex/html/_images/MKVToolNix-copytoclipboard.png
MKVBatchMultiplex/html/_images/mkvbatchmultiplex-command.png
MKVBatchMultiplex/html/_images/mkvbatchmultiplex-commandbuttons.png
MKVBatchMultiplex/html/_images/mkvbatchmultiplex-renameindex.png
MKVBatchMultiplex/html/_images/mkvbatchmultiplex-renameseriesepisode.png
MKVBatchMultiplex/html/_images/mkvbatchmultiplex-settings.png
MKVBatchMultiplex/html/_images/mkvbatchmultiplex-tabcommand.png
MKVBatchMultiplex/html/_images/mkvbatchmultiplex-tabjobs.png
MKVBatchMultiplex/html/_images/mkvbatchmultiplex-tabjobsbuttons.png
MKVBatchMultiplex/html/_images/mkvbatchmultiplex.png
MKVBatchMultiplex/html/_sources/CHANGELOG.rst.txt
MKVBatchMultiplex/html/_sources/LICENSE.rst.txt
MKVBatchMultiplex/html/_sources/README.rst.txt
MKVBatchMultiplex/html/_sources/acknowledgements.rst.txt
MKVBatchMultiplex/html/_sources/gettingstarted.rst.txt
MKVBatchMultiplex/html/_sources/index.rst.txt
MKVBatchMultiplex/html/_sources/installation.rst.txt
MKVBatchMultiplex/html/_sources/introduction.rst.txt
MKVBatchMultiplex/html/_sources/using.rst.txt
mkvbatchmultiplex-2.0.1.dist-info/AUTHORS
mkvbatchmultiplex-2.0.1.dist-info/LICENSE.txt
mkvbatchmultiplex-2.0.1.dist-info/METADATA
mkvbatchmultiplex-2.0.1.dist-info/WHEEL
mkvbatchmultiplex-2.0.1.dist-info/entry_points.txt
mkvbatchmultiplex-2.0.1.dist-info/top_level.txt
mkvbatchmultiplex-2.0.1.dist-info/RECORD
