Metadata-Version: 2.1
Name: mkvbatchmultiplex
Version: 2.0.1
Summary: A mkv media batch multiplex.
Home-page: https://github.com/akai10tsuki/mkvbatchmultiplex
Author: Efrain Vergara
Author-email: akai10tsuki@gmail.com
License: MIT
Project-URL: Bug Reports, https://github.com/akai10tsuki/mkvbatchmultiplex/issues
Project-URL: Source, https://github.com/akai10tsuki/mkvbatchmultiplex/
Keywords: mkv multimedia video mkvtoolnix plex
Platform: UNKNOWN
Classifier: Development Status :: 5 - Production/Stable
Classifier: Environment :: MacOS X
Classifier: Environment :: Win32 (MS Windows)
Classifier: Environment :: X11 Applications :: Qt
Classifier: Intended Audience :: Developers
Classifier: Topic :: Software Development :: Testing
Classifier: Topic :: Utilities
Classifier: License :: OSI Approved :: MIT License
Classifier: Operating System :: MacOS :: MacOS X
Classifier: Operating System :: Microsoft :: Windows :: Windows 7
Classifier: Operating System :: Microsoft :: Windows :: Windows 8
Classifier: Operating System :: Microsoft :: Windows :: Windows 8.1
Classifier: Operating System :: Microsoft :: Windows :: Windows 10
Classifier: Operating System :: POSIX :: Linux
Classifier: Programming Language :: Python :: 3.8
Classifier: Programming Language :: Python :: Implementation :: CPython
Requires-Python: >=3.8.1, <3.9
Requires-Dist: PySide2 (>=5.14)
Requires-Dist: vsutillib-files (>=1.6.0)
Requires-Dist: vsutillib-log (>=1.6.0)
Requires-Dist: vsutillib-macos (>=1.6.1)
Requires-Dist: vsutillib-media (>=1.6.1)
Requires-Dist: vsutillib-mkv (>=1.6.1)
Requires-Dist: vsutillib-process (>=1.6.0)
Requires-Dist: vsutillib-pyqt (>=1.6.1)
Requires-Dist: vsutillib-sql (>=1.6.0)
